chainsaws/__init__.py
chainsaws/aws/__init__.py
chainsaws/aws/apigateway_v1/__init__.py
chainsaws/aws/apigateway_v1/_apigateway_internal.py
chainsaws/aws/apigateway_v1/apigateway.py
chainsaws/aws/apigateway_v1/apigateway_models.py
chainsaws/aws/apigateway_v2/README.md
chainsaws/aws/apigateway_v2/__init__.py
chainsaws/aws/apigateway_v2/_apigateway_internal.py
chainsaws/aws/apigateway_v2/apigateway.py
chainsaws/aws/apigateway_v2/apigateway_models.py
chainsaws/aws/apigatewaymanagement/__init__.py
chainsaws/aws/apigatewaymanagement/_apigatewaymanagement_internal.py
chainsaws/aws/apigatewaymanagement/apigatewaymanagement.py
chainsaws/aws/apigatewaymanagement/apigatewaymanagement_exceptions.py
chainsaws/aws/apigatewaymanagement/apigatewaymanagement_models.py
chainsaws/aws/apigatewaymanagement/response/GetConnectionResponse.py
chainsaws/aws/athena/README.md
chainsaws/aws/athena/__init__.py
chainsaws/aws/athena/_athena_internal.py
chainsaws/aws/athena/async_session.py
chainsaws/aws/athena/athena.py
chainsaws/aws/athena/athena_exception.py
chainsaws/aws/athena/athena_models.py
chainsaws/aws/athena/query_builder.py
chainsaws/aws/athena/session.py
chainsaws/aws/athena/template.py
chainsaws/aws/cloudfront/README.md
chainsaws/aws/cloudfront/__init__.py
chainsaws/aws/cloudfront/_cloudfront_internal.py
chainsaws/aws/cloudfront/cloudfront.py
chainsaws/aws/cloudfront/cloudfront_exception.py
chainsaws/aws/cloudfront/cloudfront_models.py
chainsaws/aws/cloudwatch/README.md
chainsaws/aws/cloudwatch/__init__.py
chainsaws/aws/cloudwatch/_cloudwatch_internal.py
chainsaws/aws/cloudwatch/cloudwatch.py
chainsaws/aws/cloudwatch/cloudwatch_models.py
chainsaws/aws/cloudwatch/handler.py
chainsaws/aws/cloudwatch/logger.py
chainsaws/aws/cloudwatch/query.py
chainsaws/aws/cognito_identity/README.md
chainsaws/aws/cognito_identity/__init__.py
chainsaws/aws/cognito_identity/_cognito_identity_internal.py
chainsaws/aws/cognito_identity/cognito_identity.py
chainsaws-0.0.159.dist-info/METADATA
chainsaws-0.0.159.dist-info/WHEEL
chainsaws-0.0.159.dist-info/licenses/LICENSE.txt
chainsaws-0.0.159.dist-info/RECORD
