Metadata-Version: 2.4
Name: chainsaws
Version: 0.0.159
Summary: CHAIN your backend with Simple AWS services
Project-URL: Homepage, https://github.com/whatisyourname0/chainsaws
Project-URL: Repository, https://github.com/whatisyourname0/chainsaws.git
Author-email: whatisyourname0 <mynameisjune111@gmail.com>
License: MIT
License-File: LICENSE.txt
Classifier: Development Status :: 3 - Alpha
Classifier: Intended Audience :: Developers
Classifier: License :: OSI Approved :: MIT License
Classifier: Programming Language :: Python :: 3
Classifier: Programming Language :: Python :: 3.12
Requires-Python: >=3.12
Requires-Dist: boto3>=1.42.9
Requires-Dist: botocore>=1.42.9
Requires-Dist: croniter>=5.0.1
Requires-Dist: orjson>=3.11.5
Provides-Extra: all
Requires-Dist: gremlinpython>=3.7.0; extra == 'all'
Requires-Dist: psycopg2>=2.9.10; extra == 'all'
Requires-Dist: pymemcache>=4.0.0; extra == 'all'
Requires-Dist: redis>=5.2.1; extra == 'all'
Provides-Extra: elasticache
Requires-Dist: pymemcache>=4.0.0; extra == 'elasticache'
Requires-Dist: redis>=5.2.1; extra == 'elasticache'
Provides-Extra: neptune
Requires-Dist: gremlinpython>=3.7.0; extra == 'neptune'
Provides-Extra: redshift
Requires-Dist: psycopg2>=2.9.10; extra == 'redshift'
